im_util/__init__.py
im_util-0.1.4.dist-info/DESCRIPTION.rst
im_util-0.1.4.dist-info/METADATA
im_util-0.1.4.dist-info/RECORD
im_util-0.1.4.dist-info/WHEEL
im_util-0.1.4.dist-info/metadata.json
im_util-0.1.4.dist-info/top_level.txt
